vidtrain/__init__.py
vidtrain/thresholdtrainer.py
vidtrain/datahandler/__init__.py
vidtrain/datahandler/config.py
vidtrain/datahandler/data.py
vidtrain/datahandler/interface.py
vidtrain/datahandler/loss.py
vidtrain/datahandler/models.py
vidtrain/datahandler/rotatable.py
vidtrain/gui/__init__.py
vidtrain/gui/backend.py
vidtrain/gui/interface.py
vidtrain/gui/tk.py
vidtrain/workflow/__init__.py
vidtrain/workflow/annotation.py
vidtrain/workflow/evaluation.py
vidtrain/workflow/interface.py
vidtrain/workflow/prediction.py
vidtrain/workflow/preparation.py
vidtrain/workflow/training.py
vidtrain/workflow/workflow.py
vidtrain-0.3.1.dist-info/LICENSE
vidtrain-0.3.1.dist-info/METADATA
vidtrain-0.3.1.dist-info/WHEEL
vidtrain-0.3.1.dist-info/top_level.txt
vidtrain-0.3.1.dist-info/RECORD
