Metadata-Version: 2.1
Name: vidtrain
Version: 0.3.1
Summary: Deep learning annotation training and prediction workflow for microscopy video data
Home-page: https://gitlab.com/Thawn/vidtrain
Author: Thawn
Author-email: webmaster@korten.at
License: UNKNOWN
Platform: UNKNOWN
Classifier: Programming Language :: Python :: 3
Classifier: License :: OSI Approved :: MIT License
Classifier: Operating System :: OS Independent
Requires-Python: >3.7.0
Requires-Dist: tensorflow (>2.1)
Requires-Dist: scikit-learn (>=0.22)
Requires-Dist: numpy (>=1.18)
Requires-Dist: matplotlib (>=3)
Requires-Dist: pandas (>=1)
Requires-Dist: pandastable (>=0.12)
Requires-Dist: tifffile (>=2020.5)
Requires-Dist: micdata (>=0.1)
Requires-Dist: pydot (>=1)
Provides-Extra: bioformats
Requires-Dist: python-bioformats (>=1.5) ; extra == 'bioformats'
Requires-Dist: javabridge (>=1.0.18) ; extra == 'bioformats'
